README.md
setup.py
rho_pdf_diff/__init__.py
rho_pdf_diff/document.py
rho_pdf_diff/document_creation.py
rho_pdf_diff/filter_rules.py
rho_pdf_diff/text_diff.py
rho_pdf_diff.egg-info/PKG-INFO
rho_pdf_diff.egg-info/SOURCES.txt
rho_pdf_diff.egg-info/dependency_links.txt
rho_pdf_diff.egg-info/entry_points.txt
rho_pdf_diff.egg-info/not-zip-safe
rho_pdf_diff.egg-info/requires.txt
rho_pdf_diff.egg-info/top_level.txt
rho_pdf_diff/cli/__init__.py
rho_pdf_diff/cli/rho_pdf_diff.py
rho_pdf_diff/image_construction/__init__.py
rho_pdf_diff/image_construction/annealing_page_alignment.py
rho_pdf_diff/image_construction/diff_mask.py
rho_pdf_diff/image_construction/document_diff_image.py
tests/fixtures/__init__.py