Metadata-Version: 2.1
Name: rho-pdf-diff
Version: 0.12.1
Summary: Rho AI Fork of pdf-diff
Home-page: https://bitbucket.org/rhoai/rho-pdf-diff
Maintainer: Rho AI Corporation
License: Commercial
Platform: UNKNOWN
Provides-Extra: test
Provides-Extra: dev
